cijak-1.0.1.dist-info/RECORD
cijak-1.0.1.dist-info/WHEEL
cijak-1.0.1.dist-info/top_level.txt
cijak-1.0.1.dist-info/METADATA
cijak/_native.cpython-38-darwin.so
cijak/__init__.pyi
cijak/__init__.py
cijak/_native.c
cijak/_fallback.py
