Metadata-Version: 2.1
Name: cijak
Version: 1.0.1
Summary: A high-performance Unicode-based encoding library with C extensions
Author-email: NobreHD <info@nobrehd.pt>
License: GPL-3.0-or-later
Project-URL: Homepage, https://github.com/NobreHD/Cijak
Project-URL: Issues, https://github.com/NobreHD/Cijak/issues
Classifier: Programming Language :: Python :: 3
Classifier: Programming Language :: Python :: 3.8
Classifier: Programming Language :: Python :: 3.9
Classifier: Programming Language :: Python :: 3.10
Classifier: Programming Language :: Python :: 3.11
Classifier: Programming Language :: Python :: 3.12
Classifier: Programming Language :: Python :: 3.13
Classifier: Programming Language :: Python :: 3.14
Classifier: Programming Language :: C
Classifier: Operating System :: OS Independent
Classifier: Development Status :: 5 - Production/Stable
Requires-Python: >=3.8
